{
    "name": "root",
    "gauges": {
        "DriveToGoal.Policy.Entropy.mean": {
            "value": 1.0691150426864624,
            "min": 1.064987063407898,
            "max": 1.3574116230010986,
            "count": 73
        },
        "DriveToGoal.Policy.Entropy.sum": {
            "value": 53470.72265625,
            "min": 53257.87109375,
            "max": 67244.8125,
            "count": 73
        },
        "DriveToGoal.Environment.EpisodeLength.mean": {
            "value": 791.46875,
            "min": 65.58467741935483,
            "max": 791.46875,
            "count": 73
        },
        "DriveToGoal.Environment.EpisodeLength.sum": {
            "value": 50654.0,
            "min": 48274.0,
            "max": 51298.0,
            "count": 73
        },
        "DriveToGoal.Step.mean": {
            "value": 4149959.0,
            "min": 549993.0,
            "max": 4149959.0,
            "count": 73
        },
        "DriveToGoal.Step.sum": {
            "value": 4149959.0,
            "min": 549993.0,
            "max": 4149959.0,
            "count": 73
        },
        "DriveToGoal.Policy.ExtrinsicValueEstimate.mean": {
            "value": -1031.7218017578125,
            "min": -6463.3046875,
            "max": -1031.7218017578125,
            "count": 73
        },
        "DriveToGoal.Policy.ExtrinsicValueEstimate.sum": {
            "value": -837758.0625,
            "min": -7090245.0,
            "max": -837758.0625,
            "count": 73
        },
        "DriveToGoal.Environment.CumulativeReward.mean": {
            "value": -6396.625,
            "min": -9937.64737550471,
            "max": -6396.625,
            "count": 73
        },
        "DriveToGoal.Environment.CumulativeReward.sum": {
            "value": -409384.0,
            "min": -7383672.0,
            "max": -409384.0,
            "count": 73
        },
        "DriveToGoal.Policy.ExtrinsicReward.mean": {
            "value": -6396.625,
            "min": -9937.64737550471,
            "max": -6396.625,
            "count": 73
        },
        "DriveToGoal.Policy.ExtrinsicReward.sum": {
            "value": -409384.0,
            "min": -7383672.0,
            "max": -409384.0,
            "count": 73
        },
        "DriveToGoal.Losses.PolicyLoss.mean": {
            "value": 0.02391831948654726,
            "min": 0.02000066333426124,
            "max": 0.026592629031511023,
            "count": 73
        },
        "DriveToGoal.Losses.PolicyLoss.sum": {
            "value": 0.1195915974327363,
            "min": 0.08313836556335445,
            "max": 0.1329631451575551,
            "count": 73
        },
        "DriveToGoal.Losses.ValueLoss.mean": {
            "value": 325193.22583333333,
            "min": 325193.22583333333,
            "max": 1409208.6666666667,
            "count": 73
        },
        "DriveToGoal.Losses.ValueLoss.sum": {
            "value": 1625966.1291666667,
            "min": 1625966.1291666667,
            "max": 7046043.333333334,
            "count": 73
        },
        "DriveToGoal.Policy.LearningRate.mean": {
            "value": 0.0002975242138652624,
            "min": 0.0002975242138652624,
            "max": 0.00029968432270522575,
            "count": 73
        },
        "DriveToGoal.Policy.LearningRate.sum": {
            "value": 0.0014876210693263118,
            "min": 0.0011907004992998344,
            "max": 0.0014982829961723346,
            "count": 73
        },
        "DriveToGoal.Policy.Epsilon.mean": {
            "value": 0.19917473768,
            "min": 0.19917473768,
            "max": 0.19989477420000004,
            "count": 73
        },
        "DriveToGoal.Policy.Epsilon.sum": {
            "value": 0.9958736884,
            "min": 0.7969001653999999,
            "max": 0.9994276652000001,
            "count": 73
        },
        "DriveToGoal.Policy.Beta.mean": {
            "value": 0.004958819410231999,
            "min": 0.004958819410231999,
            "max": 0.00499474923258,
            "count": 73
        },
        "DriveToGoal.Policy.Beta.sum": {
            "value": 0.024794097051159997,
            "min": 0.019845318253459997,
            "max": 0.02497144049348,
            "count": 73
        },
        "DriveToGoal.IsTraining.mean": {
            "value": 1.0,
            "min": 1.0,
            "max": 1.0,
            "count": 73
        },
        "DriveToGoal.IsTraining.sum": {
            "value": 1.0,
            "min": 1.0,
            "max": 1.0,
            "count": 73
        }
    },
    "metadata": {
        "timer_format_version": "0.1.0",
        "start_time_seconds": "1663535730",
        "python_version": "3.7.14 (default, Sep  6 2022, 23:37:35) \n[Clang 13.1.6 (clang-1316.0.21.2.5)]",
        "command_line_arguments": "/Users/iakalann/Documents/ReinforcementLearning/self-driving/venv37/bin/mlagents-learn config/ppo/DriveScene.yaml --run-id=DriveToGoal1.1.2 --resume",
        "mlagents_version": "0.29.0",
        "mlagents_envs_version": "0.29.0",
        "communication_protocol_version": "1.5.0",
        "pytorch_version": "1.8.1",
        "numpy_version": "1.21.2",
        "end_time_seconds": "1663582965"
    },
    "total": 47233.565937024,
    "count": 1,
    "self": 0.011546221001481172,
    "children": {
        "run_training.setup": {
            "total": 0.042783409000000105,
            "count": 1,
            "self": 0.042783409000000105
        },
        "TrainerController.start_learning": {
            "total": 47233.511607394,
            "count": 1,
            "self": 98.05036158634903,
            "children": {
                "TrainerController._reset_env": {
                    "total": 19.634037695,
                    "count": 1,
                    "self": 19.634037695
                },
                "TrainerController.advance": {
                    "total": 47115.69186432865,
                    "count": 3703389,
                    "self": 104.60416991556849,
                    "children": {
                        "env_step": {
                            "total": 41684.00925174978,
                            "count": 3703389,
                            "self": 37342.91785911773,
                            "children": {
                                "SubprocessEnvManager._take_step": {
                                    "total": 4255.467313297595,
                                    "count": 3703389,
                                    "self": 251.95105863646586,
                                    "children": {
                                        "TorchPolicy.evaluate": {
                                            "total": 4003.516254661129,
                                            "count": 3687537,
                                            "self": 557.8734175791969,
                                            "children": {
                                                "TorchPolicy.sample_actions": {
                                                    "total": 3445.642837081932,
                                                    "count": 3687537,
                                                    "self": 3445.642837081932
                                                }
                                            }
                                        }
                                    }
                                },
                                "workers": {
                                    "total": 85.62407933445111,
                                    "count": 3703388,
                                    "self": 0.0,
                                    "children": {
                                        "worker_root": {
                                            "total": 47012.00777502825,
                                            "count": 3703388,
                                            "is_parallel": true,
                                            "self": 13622.473582661922,
                                            "children": {
                                                "run_training.setup": {
                                                    "total": 0.0,
                                                    "count": 0,
                                                    "is_parallel": true,
                                                    "self": 0.0,
                                                    "children": {
                                                        "steps_from_proto": {
                                                            "total": 0.03440627599999857,
                                                            "count": 1,
                                                            "is_parallel": true,
                                                            "self": 0.0005944110000015712,
                                                            "children": {
                                                                "_process_maybe_compressed_observation": {
                                                                    "total": 0.0335610399999986,
                                                                    "count": 2,
                                                                    "is_parallel": true,
                                                                    "self": 0.00020987799999971912,
                                                                    "children": {
                                                                        "_observation_to_np_array": {
                                                                            "total": 0.03335116199999888,
                                                                            "count": 1,
                                                                            "is_parallel": true,
                                                                            "self": 7.311299999912535e-05,
                                                                            "children": {
                                                                                "process_pixels": {
                                                                                    "total": 0.033278048999999754,
                                                                                    "count": 1,
                                                                                    "is_parallel": true,
                                                                                    "self": 0.0013446059999999704,
                                                                                    "children": {
                                                                                        "image_decompress": {
                                                                                            "total": 0.031933442999999784,
                                                                                            "count": 1,
                                                                                            "is_parallel": true,
                                                                                            "self": 0.031933442999999784
                                                                                        }
                                                                                    }
                                                                                }
                                                                            }
                                                                        }
                                                                    }
                                                                },
                                                                "_process_rank_one_or_two_observation": {
                                                                    "total": 0.00025082499999840024,
                                                                    "count": 2,
                                                                    "is_parallel": true,
                                                                    "self": 0.00025082499999840024
                                                                }
                                                            }
                                                        },
                                                        "UnityEnvironment.step": {
                                                            "total": 0.045020294000000405,
                                                            "count": 1,
                                                            "is_parallel": true,
                                                            "self": 0.0002726180000003353,
                                                            "children": {
                                                                "UnityEnvironment._generate_step_input": {
                                                                    "total": 0.0003026430000012681,
                                                                    "count": 1,
                                                                    "is_parallel": true,
                                                                    "self": 0.0003026430000012681
                                                                },
                                                                "communicator.exchange": {
                                                                    "total": 0.04315796599999899,
                                                                    "count": 1,
                                                                    "is_parallel": true,
                                                                    "self": 0.04315796599999899
                                                                },
                                                                "steps_from_proto": {
                                                                    "total": 0.0012870669999998086,
                                                                    "count": 1,
                                                                    "is_parallel": true,
                                                                    "self": 0.0002587760000025696,
                                                                    "children": {
                                                                        "_process_maybe_compressed_observation": {
                                                                            "total": 0.0008764939999963417,
                                                                            "count": 2,
                                                                            "is_parallel": true,
                                                                            "self": 0.0001231489999931057,
                                                                            "children": {
                                                                                "_observation_to_np_array": {
                                                                                    "total": 0.000753345000003236,
                                                                                    "count": 1,
                                                                                    "is_parallel": true,
                                                                                    "self": 7.488500000363274e-05,
                                                                                    "children": {
                                                                                        "process_pixels": {
                                                                                            "total": 0.0006784599999996033,
                                                                                            "count": 1,
                                                                                            "is_parallel": true,
                                                                                            "self": 0.0003230139999992332,
                                                                                            "children": {
                                                                                                "image_decompress": {
                                                                                                    "total": 0.0003554460000003701,
                                                                                                    "count": 1,
                                                                                                    "is_parallel": true,
                                                                                                    "self": 0.0003554460000003701
                                                                                                }
                                                                                            }
                                                                                        }
                                                                                    }
                                                                                }
                                                                            }
                                                                        },
                                                                        "_process_rank_one_or_two_observation": {
                                                                            "total": 0.00015179700000089724,
                                                                            "count": 2,
                                                                            "is_parallel": true,
                                                                            "self": 0.00015179700000089724
                                                                        }
                                                                    }
                                                                }
                                                            }
                                                        }
                                                    }
                                                },
                                                "UnityEnvironment.step": {
                                                    "total": 33389.53419236633,
                                                    "count": 3703387,
                                                    "is_parallel": true,
                                                    "self": 419.7856195004497,
                                                    "children": {
                                                        "UnityEnvironment._generate_step_input": {
                                                            "total": 270.6302892032472,
                                                            "count": 3703387,
                                                            "is_parallel": true,
                                                            "self": 270.6302892032472
                                                        },
                                                        "communicator.exchange": {
                                                            "total": 29857.34522666233,
                                                            "count": 3703387,
                                                            "is_parallel": true,
                                                            "self": 29857.34522666233
                                                        },
                                                        "steps_from_proto": {
                                                            "total": 2841.773057000304,
                                                            "count": 3703387,
                                                            "is_parallel": true,
                                                            "self": 612.2334888357477,
                                                            "children": {
                                                                "_process_maybe_compressed_observation": {
                                                                    "total": 1955.024168093492,
                                                                    "count": 7406774,
                                                                    "is_parallel": true,
                                                                    "self": 166.81787233580803,
                                                                    "children": {
                                                                        "_observation_to_np_array": {
                                                                            "total": 1788.206295757684,
                                                                            "count": 3703387,
                                                                            "is_parallel": true,
                                                                            "self": 100.11732234221472,
                                                                            "children": {
                                                                                "process_pixels": {
                                                                                    "total": 1688.0889734154694,
                                                                                    "count": 3703387,
                                                                                    "is_parallel": true,
                                                                                    "self": 776.3294832545618,
                                                                                    "children": {
                                                                                        "image_decompress": {
                                                                                            "total": 911.7594901609076,
                                                                                            "count": 3703387,
                                                                                            "is_parallel": true,
                                                                                            "self": 911.7594901609076
                                                                                        }
                                                                                    }
                                                                                }
                                                                            }
                                                                        }
                                                                    }
                                                                },
                                                                "_process_rank_one_or_two_observation": {
                                                                    "total": 274.5154000710642,
                                                                    "count": 7406774,
                                                                    "is_parallel": true,
                                                                    "self": 274.5154000710642
                                                                }
                                                            }
                                                        }
                                                    }
                                                }
                                            }
                                        }
                                    }
                                }
                            }
                        },
                        "trainer_advance": {
                            "total": 5327.078442663299,
                            "count": 3703388,
                            "self": 114.929287327147,
                            "children": {
                                "process_trajectory": {
                                    "total": 502.0914884811007,
                                    "count": 3703388,
                                    "self": 501.2176563211004,
                                    "children": {
                                        "RLTrainer._checkpoint": {
                                            "total": 0.8738321600003474,
                                            "count": 7,
                                            "self": 0.8738321600003474
                                        }
                                    }
                                },
                                "_update_policy": {
                                    "total": 4710.057666855051,
                                    "count": 359,
                                    "self": 840.2578871896667,
                                    "children": {
                                        "TorchPPOOptimizer.update": {
                                            "total": 3869.7997796653844,
                                            "count": 10770,
                                            "self": 3869.7997796653844
                                        }
                                    }
                                }
                            }
                        }
                    }
                },
                "TrainerController._save_models": {
                    "total": 0.13534378400072455,
                    "count": 1,
                    "self": 0.001628898004128132,
                    "children": {
                        "RLTrainer._checkpoint": {
                            "total": 0.13371488599659642,
                            "count": 1,
                            "self": 0.13371488599659642
                        }
                    }
                }
            }
        }
    }
}